shapley_lz.py
shapley_lz_bruteforce.py
shapley_lz_multiproc.py
shapley_lz/__init__.py
shapley_lz/explainer/__init__.py
shapley_lz/explainer/shapley_lz.py
shapley_lz/variants/__init__.py
shapley_lz/variants/shapley_lz_bruteforce.py
shapley_lz/variants/shapley_lz_multiproc.py
shapley_lz-0.0.11.dist-info/METADATA
shapley_lz-0.0.11.dist-info/WHEEL
shapley_lz-0.0.11.dist-info/top_level.txt
shapley_lz-0.0.11.dist-info/RECORD
